LabL/yMux1.v
module mux1(z, a, b, c);
    output z;
    input a, b, c;
    wire notC, upper, lower;
    not (notC, c);    // C is the input not is the wire output connecting to the first AND 
    and first_and(upper, b, c);
    and sec_and(lower, a, notC);
    or ( z, upper, lower); // this will or togther the results//and (T1, D1, S), (T2, D0, Sbar);
//not (Sbar, S);
//or (Y, T1, T2);
endmodule

CPU_Components/yMux2.v
`include "yMux1.v"

module yMux2(z, a, b, c);
    
    output [1:0] z;
    input [1:0] a, b;
    input c;
    mux1 first_and( z[0], a[0], b[0], c);
    mux1 sec_and( z[1], a[1], b[1], c);
endmodule

CPU_Components/labL2.v
`timescale 1ns/1ns
`include "yMux2.v"
// to display this use sudo apt install gtkwave
// open with $gtkwave 
// run this file from 
module labL2;
    wire [1:0] z;
    integer i, j, k;

    reg[1:0] a, b ;
    reg c;

    yMux2 UUT(z, a, b, c);
    
    initial begin
        $dumpfile("labL2.vcd");
        $dumpvars(0, labL2);

        for (i = 0; i < 4; i = i + 1)
        begin
            for (j = 0; j < 4; j++)
            begin
                for(k = 0; k < 2; k++)
                begin
                    a = i;
                    b = j;
                    c = k;
                    #20;
                    
                    if(c == 0 && z == b) $display("pass c0");
                    else if( c == 1 && z == a) $display("pass c1");
                    else $display("fail a=%d b=%d c=%d z=%b", i, j, k, z);
                end            
            end 
        end
        $finish;
    end



endmodule

CPU_Components/labL2.vcd
$date
	Mon Nov 14 17:31:27 2022
$end
$version
	Icarus Verilog
$end
$timescale
	1ns
$end
$scope module labL2 $end
$var wire 2 ! z [1:0] $end
$var reg 2 " a [1:0] $end
$var reg 2 # b [1:0] $end
$var reg 1 $ c $end
$var integer 32 % i [31:0] $end
$var integer 32 & j [31:0] $end
$var integer 32 ' k [31:0] $end
$scope module UUT $end
$var wire 2 ( a [1:0] $end
$var wire 2 ) b [1:0] $end
$var wire 1 $ c $end
$var wire 2 * z [1:0] $end
$scope module first_and $end
$var wire 1 + a $end
$var wire 1 , b $end
$var wire 1 $ c $end
$var wire 1 - lower $end
$var wire 1 . notC $end
$var wire 1 / upper $end
$var wire 1 0 z $end
$upscope $end
$scope module sec_and $end
$var wire 1 1 a $end
$var wire 1 2 b $end
$var wire 1 $ c $end
$var wire 1 3 lower $end
$var wire 1 4 notC $end
$var wire 1 5 upper $end
$var wire 1 6 z $end
$upscope $end
$upscope $end
$upscope $end
$enddefinitions $end
#0
$dumpvars
06
05
14
03
02
01
00
0/
1.
0-
0,
0+
b0 *
b0 )
b0 (
b0 '
b0 &
b0 %
0$
b0 #
b0 "
b0 !
$end
#20
0.
04
1$
b1 '
#40
b1 !
b1 *
10
1/
1.
14
1,
0$
b1 #
b1 )
b1 &
b0 '
#60
b0 !
b0 *
00
0/
0.
04
1$
b1 '
#80
b10 !
b10 *
16
15
1.
14
0,
12
0$
b10 #
b10 )
b10 &
b0 '
#100
b0 !
b0 *
06
05
0.
04
1$
b1 '
#120
16
b11 !
b11 *
10
15
1/
1.
14
1,
0$
b11 #
b11 )
b11 &
b0 '
#140
00
b0 !
b0 *
06
0/
05
0.
04
1$
b1 '
#160
1.
14
0,
02
1+
0$
b0 #
b0 )
b1 "
b1 (
b1 %
b0 &
b0 '
#180
b1 !
b1 *
10
0.
1-
04
1$
b1 '
#200
1/
1.
0-
14
1,
0$
b1 #
b1 )
b1 &
b0 '
#220
0/
0.
1-
04
1$
b1 '
#240
16
b10 !
b10 *
00
15
1.
0-
14
0,
12
0$
b10 #
b10 )
b10 &
b0 '
#260
06
b1 !
b1 *
10
05
0.
1-
04
1$
b1 '
#280
b11 !
b11 *
16
15
1/
1.
0-
14
1,
0$
b11 #
b11 )
b11 &
b0 '
#300
b1 !
b1 *
06
0/
05
0.
1-
04
1$
b1 '
#320
b0 !
b0 *
00
1.
0-
14
0,
02
0+
11
0$
b0 #
b0 )
b10 "
b10 (
b10 %
b0 &
b0 '
#340
b10 !
b10 *
16
0.
04
13
1$
b1 '
#360
10
b1 !
b1 *
06
1/
1.
14
03
1,
0$
b1 #
b1 )
b1 &
b0 '
#380
00
0/
b10 !
b10 *
16
0.
04
13
1$
b1 '
#400
15
1.
14
03
0,
12
0$
b10 #
b10 )
b10 &
b0 '
#420
05
0.
04
13
1$
b1 '
#440
10
15
b11 !
b11 *
16
1/
1.
14
03
1,
0$
b11 #
b11 )
b11 &
b0 '
#460
b10 !
b10 *
00
0/
05
0.
04
13
1$
b1 '
#480
b0 !
b0 *
06
1.
14
03
0,
02
1+
0$
b0 #
b0 )
b11 "
b11 (
b11 %
b0 &
b0 '
#500
10
b11 !
b11 *
16
0.
1-
04
13
1$
b1 '
#520
b1 !
b1 *
06
1/
1.
0-
14
03
1,
0$
b1 #
b1 )
b1 &
b0 '
#540
0/
b11 !
b11 *
16
0.
1-
04
13
1$
b1 '
#560
b10 !
b10 *
00
15
1.
0-
14
03
0,
12
0$
b10 #
b10 )
b10 &
b0 '
#580
b11 !
b11 *
10
05
0.
1-
04
13
1$
b1 '
#600
15
b11 !
b11 *
16
1/
1.
0-
14
03
1,
0$
b11 #
b11 )
b11 &
b0 '
#620
0/
05
0.
1-
04
13
1$
b1 '
#640
b100 %
b100 &
b10 '
