LabL/yMux1.v
module mux1(z, a, b, c);
    output z;
    input a, b, c;
    wire notC, upper, lower;
    not (notC, c);    // C is the input not is the wire output connecting to the first AND 
    and first_and(upper, b, c);
    and sec_and(lower, a, notC);
    or ( z, upper, lower); // this will or togther the results//and (T1, D1, S), (T2, D0, Sbar);
//not (Sbar, S);
//or (Y, T1, T2);
endmodule

CPU_Components/labL1.v
`timescale 1ns/1ns
`include "yMux1.v"
// to display this use sudo apt install gtkwave
// open with $gtkwave 
// run this file from 
module labL1;
    wire z;
    integer i, j, k;

    reg a, b, c;
    mux1 UUT(z, a, b, c);
    
    initial begin
        $dumpfile("labL1.vcd");
        $dumpvars(0, labL1);

        for (i = 0; i < 2; i = i + 1)
        begin
            for (j = 0; j < 2; j++)
            begin
                for(k = 0; k < 2; k++)
                begin
                    a = i;
                    b = j;
                    c = k;
                    #20;
                    //$display("i=%5d j=%5d k=%5d\n", i, j, k);

                    if( c === 0 && z === a) $display("pass c0");
                    else if( c === 1 && z === b) $display("pass c1");
                    else $display("fail a=%1b b=%1b c=%1b z=%b", i, j, k, z);

                
                end            
            end 
        end
        $finish;
    end



endmodule

CPU_Components/labL1.vcd
$date
	Wed Nov 16 14:26:22 2022
$end
$version
	Icarus Verilog
$end
$timescale
	1ns
$end
$scope module labL1 $end
$var wire 1 ! z $end
$var reg 1 " a $end
$var reg 1 # b $end
$var reg 1 $ c $end
$var integer 32 % i [31:0] $end
$var integer 32 & j [31:0] $end
$var integer 32 ' k [31:0] $end
$scope module UUT $end
$var wire 1 " a $end
$var wire 1 # b $end
$var wire 1 $ c $end
$var wire 1 ( lower $end
$var wire 1 ) notC $end
$var wire 1 * upper $end
$var wire 1 ! z $end
$upscope $end
$upscope $end
$enddefinitions $end
#0
$dumpvars
0*
1)
0(
b0 '
b0 &
b0 %
0$
0#
0"
0!
$end
#20
0)
1$
b1 '
#40
1)
0$
1#
b1 &
b0 '
#60
1!
0)
1*
1$
b1 '
#80
1(
1!
1)
0*
0$
0#
1"
b1 %
b0 &
b0 '
#100
0!
0(
0)
1$
b1 '
#120
1!
1(
1)
0$
1#
b1 &
b0 '
#140
0(
0)
1*
1$
b1 '
#160
b10 %
b10 &
b10 '
